setup.py
bitpit/__init__.py
bitpit/__main__.py
bitpit.egg-info/PKG-INFO
bitpit.egg-info/SOURCES.txt
bitpit.egg-info/dependency_links.txt
bitpit.egg-info/requires.txt
bitpit.egg-info/top_level.txt