Metadata-Version: 1.1
Name: bitpit
Version: 0.0.3
Summary: event driven http download library with automatic resume and other features.
Home-page: UNKNOWN
Author: Mohammad Alghafli
Author-email: thebsom@gmail.com
License: UNKNOWN
Keywords: download manager
Platform: UNKNOWN
Classifier: Development Status :: 3 - Alpha
Classifier: Intended Audience :: Developers
Classifier: License :: OSI Approved :: GNU General Public License v3 (GPLv3)
Classifier: Programming Language :: Python :: 3.4
